<?xml version="1.0" encoding="utf-8"?><xml PATH="/home/java/trinity/trinity-en/WEB-INF/Anaconda/WebViewDir/sa@sdlc.bestmember.net/WC_SEQ_102740999071361075199810-Anaconda-Backup-Recovery.xml" USER="null" id="WC_SEQ_102740999071361075199810"><WC_SEQ_102740999071361075199810 VIEWCOLLECTION_KOR_NAME="아나콘다 백업-원복"><V_SEQ_101665986251361075217648 LAYOUT_TYPE="BASIC_PATH" VIEW_BODY="/jsp/anaconda/anaconda_backup.jsp" VIEW_COLLECTION_NAME="WC_SEQ_102740999071361075199810" VIEW_DESC="아나콘다 백업-원복 관리" VIEW_FOOTER="/jsp/anaconda/anaconda_footer.jsp" VIEW_FORWARD_KOR_NAME="아나콘다 백업-원복 관리" VIEW_FORWARD_NAME="V_SEQ_101665986251361075217648" VIEW_LAYOUT="/jsp/anaconda/anaconda_layout.jsp" VIEW_LEFT="" VIEW_RIGHT="/jsp/anaconda/anaconda_right.jsp" VIEW_TOP="/jsp/anaconda/anaconda_top.jsp" VIEW_TYPE="FORWARD" XTREME_USE_YN="Y"><![CDATA[아나콘다 백업-원복 관리]]></V_SEQ_101665986251361075217648><V_SEQ_106818673031361075445670 VIEW_BODY="" VIEW_DESC="아나콘다 백업-원복 프로세스" VIEW_FOOTER="" VIEW_FORWARD_KOR_NAME="아나콘다 백업-원복 프로세스" VIEW_FORWARD_NAME="V_SEQ_106818673031361075445670" VIEW_LAYOUT="" VIEW_LEFT="" VIEW_RIGHT="" VIEW_TOP=""><![CDATA[아나콘다 백업-원복 프로세스]]></V_SEQ_106818673031361075445670><V_SEQ_106942265141361085604567 LAYOUT_TYPE="BASIC_PATH" VIEW_BODY="" VIEW_COLLECTION_NAME="WC_SEQ_102740999071361075199810" VIEW_DESC="백업파일 보기" VIEW_FOOTER="" VIEW_FORWARD_KOR_NAME="백업파일 보기" VIEW_FORWARD_NAME="V_SEQ_106942265141361085604567" VIEW_LAYOUT="/jsp/anaconda/anaconda_backup_view.jsp" VIEW_LEFT="" VIEW_RIGHT="" VIEW_TOP="" VIEW_TYPE="FORWARD" XTREME_USE_YN="Y"><![CDATA[백업파일 보기]]></V_SEQ_106942265141361085604567></WC_SEQ_102740999071361075199810></xml>