<?xml version="1.0" encoding="utf-8"?><xml PATH="/usr/local/tomcat/webapps/trinity/WEB-INF/Anaconda/BizDir/sp.bestmember.net/BC_SEQ_108612582261516366897155.xml" USER="null" id="BC_SEQ_108612582261516366897155"><BC_SEQ_108612582261516366897155 AnacondaRule="null" BIZ_COLLECTION_CACHE_TIME="0" BIZ_COLLECTION_COUNT="1" BIZ_COLLECTION_KOR_NAME="비밀번호 변경" COLLECTION_INTERCEPTER="" KIND="COLLECTION" aop_intercepter="" aop_point_class="&lt;BR&gt;&lt;BR&gt;&lt;BR&gt;&lt;BR&gt;" aop_point_method="&lt;BR&gt;&lt;BR&gt;&lt;BR&gt;&lt;BR&gt;" business_rule="null" id="BC_SEQ_108612582261516366897155" referenceKey="null"><modifyPassword DATASOURCE="java:comp/env/jdbc/SPDB" KIND="DATA" OWNER="sa" REMOTE="false" SERVICE_NAME="Update Member&lt;BR&gt;Set Password = SHA2(?,256)&lt;BR&gt;Where Account = ?" TYPE="SQL">
<FIELD KIND="ITEM" LENGTH="0" NAME="password" SEQ="1" TYPE="STRING" VALUE=""/>
<FIELD KIND="ITEM" LENGTH="0" NAME="session.Account" SEQ="2" TYPE="STRING" VALUE=""/>
</modifyPassword><updateCallBack DATASOURCE="java:comp/env/jdbc/SPDB" KIND="DATA" OWNER="sa" REMOTE="false" SERVICE_NAME="UPDATE ChatBotToken&lt;BR&gt;SET callback = ? , domain = ?&lt;BR&gt;WHERE Account = ?" TYPE="SQL" aop_intercepter="com.stuko.anaconda.intercepter.ConditionalBusinessIntercepter" aop_point_class="(request.getFieldValue(&quot;callback&quot;) != null &amp;&amp; request.getFieldValue(&quot;callback&quot;) != '') ||  (request.getFieldValue(&quot;domain&quot;) != null &amp;&amp; request.getFieldValue(&quot;domain&quot;) != '')">
<FIELD KIND="ITEM" LENGTH="0" NAME="callback" SEQ="1" TYPE="STRING" VALUE=""/>
<FIELD KIND="ITEM" LENGTH="0" NAME="domain" SEQ="2" TYPE="STRING" VALUE=""/>
<FIELD KIND="ITEM" LENGTH="0" NAME="session.Account" SEQ="3" TYPE="STRING" VALUE=""/>
</updateCallBack></BC_SEQ_108612582261516366897155></xml>